moba_cache-1.3.dist-info/DESCRIPTION.rst
moba_cache-1.3.dist-info/METADATA
moba_cache-1.3.dist-info/RECORD
moba_cache-1.3.dist-info/WHEEL
moba_cache-1.3.dist-info/metadata.json
moba_cache-1.3.dist-info/top_level.txt
mobacache/__init__.py
mobacache/base.py
mobacache/cache.py
